{"cameraMode":{"drawMode":0,"name":"Shaded","section":"Shading Mode"},"sceneLighting":true,"audioPlay":false,"sceneViewState":{"m_AlwaysRefresh":false,"showFog":true,"showSkybox":false,"showFlares":true,"showImageEffects":true,"showParticleSystems":true,"showVisualEffectGraphs":true,"m_FxEnabled":true},"in2DMode":false,"pivot":{"x":-35.1497917175293,"y":1.918959379196167,"z":-65.25971984863281},"rotation":{"x":-0.060031428933143619,"y":0.8759304881095886,"z":-0.11277931183576584,"w":-0.465372771024704},"size":0.720057487487793,"orthographic":false}